README.md
setup.py
gemstool/__init__.py
gemstool/get_draft_from_template.py
gemstool/mapIDsViaMNXref.py
gemstool/merge_model.py
gemstool/model_refine.py
gemstool/model_report.py
gemstool/seq_ana.py
gemstool/venn3_samesize.py
gemstool.egg-info/PKG-INFO
gemstool.egg-info/SOURCES.txt
gemstool.egg-info/dependency_links.txt
gemstool.egg-info/top_level.txt
gemstool/io/__init__.py
gemstool/io/convert_model.py