Metadata-Version: 2.1
Name: gemstool
Version: 0.0.2
Summary: some small tools for my modeling work
Home-page: https://github.com/HaoLuoChalmers/gemstool
Author: Hao Luo
Author-email: bioluohao@outlook.com
License: UNKNOWN
Platform: UNKNOWN
Classifier: Programming Language :: Python :: 3
Classifier: Operating System :: OS Independent
Requires-Python: >=3.6
